Metadata-Version: 1.1
Name: peewee2click
Version: 0.0.4
Summary: UNKNOWN
Home-page: https://github.com/buguroo/peewee2click
Author: Samuel Herrero Bartolomé
Author-email: sherrero@buguroo.com
License: LGPLv3
Keywords: peewee click arguments conversor
Platform: UNKNOWN
Classifier: Development Status :: 4 - Beta
Classifier: Programming Language :: Python :: 3.4
Classifier: Programming Language :: Python :: 3.5
Classifier: Programming Language :: Python :: 3.6
